phpserialize.py
phpserialize_typed-1.0.0.dist-info/licenses/LICENSE
phpserialize_typed-1.0.0.dist-info/METADATA
phpserialize_typed-1.0.0.dist-info/WHEEL
phpserialize_typed-1.0.0.dist-info/top_level.txt
phpserialize_typed-1.0.0.dist-info/RECORD
