Metadata-Version: 2.4
Name: phpserialize-typed
Version: 1.0.0
Summary: A PHP serializer/unserializer for Python with comprehensive type annotations
Author-email: Howard Yang <pc028771@users.noreply.github.com>
Maintainer-email: Howard Yang <pc028771@users.noreply.github.com>
License-Expression: BSD-3-Clause
Project-URL: Homepage, https://github.com/pc028771/phpserialize-typed
Project-URL: Repository, https://github.com/pc028771/phpserialize-typed
Project-URL: Issues, https://github.com/pc028771/phpserialize-typed/issues
Project-URL: Changelog, https://github.com/pc028771/phpserialize-typed/blob/master/CHANGELOG.md
Project-URL: Original Project, https://github.com/mitsuhiko/phpserialize
Keywords: php,serialize,unserialize,serialization,typing,type-hints,php-serialization,data-interchange,typed
Classifier: Development Status :: 4 - Beta
Classifier: Intended Audience :: Developers
Classifier: Operating System :: OS Independent
Classifier: Programming Language :: Python
Classifier: Programming Language :: Python :: 3
Classifier: Programming Language :: Python :: 3.7
Classifier: Programming Language :: Python :: 3.8
Classifier: Programming Language :: Python :: 3.9
Classifier: Programming Language :: Python :: 3.10
Classifier: Programming Language :: Python :: 3.11
Classifier: Programming Language :: Python :: 3.12
Classifier: Typing :: Typed
Requires-Python: >=3.7
License-File: LICENSE
Provides-Extra: dev
Requires-Dist: pytest>=7.0.0; extra == "dev"
Requires-Dist: pytest-cov>=4.0.0; extra == "dev"
Requires-Dist: mypy>=1.0.0; extra == "dev"
Dynamic: license-file
